sprockets.mixins.metrics-0.9.0-py2.7-nspkg.pth
examples/__init__.py
examples/influxdb.py
examples/statsd.py
sprockets/mixins/metrics/__init__.py
sprockets/mixins/metrics/influxdb.py
sprockets/mixins/metrics/statsd.py
sprockets/mixins/metrics/testing.py
sprockets.mixins.metrics-0.9.0.dist-info/DESCRIPTION.rst
sprockets.mixins.metrics-0.9.0.dist-info/METADATA
sprockets.mixins.metrics-0.9.0.dist-info/metadata.json
sprockets.mixins.metrics-0.9.0.dist-info/namespace_packages.txt
sprockets.mixins.metrics-0.9.0.dist-info/RECORD
sprockets.mixins.metrics-0.9.0.dist-info/top_level.txt
sprockets.mixins.metrics-0.9.0.dist-info/WHEEL
sprockets.mixins.metrics-0.9.0.dist-info/zip-safe
